<?xml version="1.0" encoding="UTF-8"?>
<ParamSection>
	<ParamSectHeader>
		<AutoHotspots>false</AutoHotspots>
		<StatBits>
			<STBit_FixSize/>
		</StatBits>
		<WDLeftFrame>0</WDLeftFrame>
		<WDRightFrame>0</WDRightFrame>
		<WDTopFrame>0</WDTopFrame>
		<WDBotFrame>0</WDBotFrame>
		<LayFlags>0</LayFlags>
		<WDMirrorThickness>0</WDMirrorThickness>
		<WDWallInset>0</WDWallInset>
	</ParamSectHeader>
	<Parameters SectVersion="27" SectionFlags="0" SubIdent="0">
		<Length Name="A">
			<Description><![CDATA["Dimension 1"]]></Description>
			<Fix/>
			<Value>1</Value>
		</Length>
		<Length Name="B">
			<Description><![CDATA["Dimension 2"]]></Description>
			<Fix/>
			<Value>1</Value>
		</Length>
		<Length Name="ZZYZX">
			<Description><![CDATA["Height"]]></Description>
			<Fix/>
			<Value>1</Value>
		</Length>
		<Boolean Name="AC_show2DHotspotsIn3D">
			<Description><![CDATA["Show 2D Hotspots in 3D"]]></Description>
			<Fix/>
			<Flags>
				<ParFlg_Hidden/>
			</Flags>
			<Value>0</Value>
		</Boolean>
		<Length Name="ac_bottomlevel">
			<Description><![CDATA["Bottom Level"]]></Description>
			<Fix/>
			<Flags>
				<ParFlg_Hidden/>
			</Flags>
			<Value>1</Value>
		</Length>
		<Length Name="ac_toplevel">
			<Description><![CDATA["Top Level"]]></Description>
			<Fix/>
			<Flags>
				<ParFlg_Hidden/>
			</Flags>
			<Value>0</Value>
		</Length>
		<Integer Name="gs_gutter_ds_profile_num">
			<Description><![CDATA["Downspout Profile (1,2,3)"]]></Description>
			<Value>1</Value>
		</Integer>
		<Length Name="gs_gutter_aa">
			<Description><![CDATA["Profile Width"]]></Description>
			<Value>0.04</Value>
		</Length>
		<Length Name="gs_gutter_bb">
			<Description><![CDATA["Profile Length"]]></Description>
			<Value>0.05</Value>
		</Length>
		<Length Name="gs_gutter_dd">
			<Description><![CDATA["Profile Radius"]]></Description>
			<Value>0.05</Value>
		</Length>

		<!-- gs_3d_representation: PARAMETER BLOCK ===== PARAMETER BLOCK ===== PARAMETER BLOCK ===== PARAMETER BLOCK -->

		<Title Name="gs_3d_representation">
			<Description><![CDATA["3D Representation"]]></Description>
		</Title>
		<Integer Name="gs_detlevel_3D_m">
			<Description><![CDATA["3D Detail Level (0,1,2)"]]></Description>
			<Flags>
				<ParFlg_Child/>
			</Flags>
			<Value>2</Value>
		</Integer>
		<Integer Name="gs_resol">
			<Description><![CDATA["Resolution"]]></Description>
			<Flags>
				<ParFlg_Child/>
			</Flags>
			<Value>12</Value>
		</Integer>
		<Boolean Name="gs_shadow">
			<Description><![CDATA["Shadow"]]></Description>
			<Flags>
				<ParFlg_Child/>
			</Flags>
			<Value>1</Value>
		</Boolean>

		<!-- gs_2d_representation: PARAMETER BLOCK ===== PARAMETER BLOCK ===== PARAMETER BLOCK ===== PARAMETER BLOCK -->

		<Title Name="gs_2d_representation">
			<Description><![CDATA["2D Representation"]]></Description>
		</Title>
		<LineType Name="gs_line_type">
			<Description><![CDATA["Line Type"]]></Description>
			<Flags>
				<ParFlg_Child/>
			</Flags>
			<Value>1</Value>
		</LineType>
		<PenColor Name="gs_cont_pen">
			<Description><![CDATA["Contour Pen"]]></Description>
			<Flags>
				<ParFlg_Child/>
			</Flags>
			<Value>1</Value>
		</PenColor>
		<FillPattern Name="gs_fill_type">
			<Description><![CDATA["Fill Type"]]></Description>
			<Flags>
				<ParFlg_Child/>
			</Flags>
			<Value>65</Value>
		</FillPattern>
		<PenColor Name="gs_fill_pen">
			<Description><![CDATA["Fill Pen"]]></Description>
			<Flags>
				<ParFlg_Child/>
			</Flags>
			<Value>91</Value>
		</PenColor>
		<PenColor Name="gs_back_pen">
			<Description><![CDATA["Fill Background Pen"]]></Description>
			<Flags>
				<ParFlg_Child/>
			</Flags>
			<Value>91</Value>
		</PenColor>
		<Integer Name="gs_gutter_type">
			<Description><![CDATA[""]]></Description>
			<Flags>
				<ParFlg_Child/>
			</Flags>
			<Value>1</Value>
		</Integer>

		<!-- gs_material: PARAMETER BLOCK ===== PARAMETER BLOCK ===== PARAMETER BLOCK ===== PARAMETER BLOCK -->

		<Title Name="gs_material">
			<Description><![CDATA["Surfaces"]]></Description>
		</Title>
		<Material Name="gs_gutter_ds_h_mat">
			<Description><![CDATA["Bracket"]]></Description>
			<Flags>
				<ParFlg_Child/>
			</Flags>
			<Value>8</Value>
		</Material>
		<Length Name="dis_wall">
			<Description><![CDATA["Distance Between Downspout Axis and Wall"]]></Description>
			<Value>0</Value>
		</Length>
	</Parameters>
</ParamSection>
