<?xml version="1.0" encoding="UTF-8"?>
<Symbol IsArchivable="true" IsPlaceable="true" MainGUID="868CFE5D-D05B-4F87-A9DD-94585AB13E01" MigrationValue="Normal" Owner="1196638531" Signature="1196644685" Version="38">
<Ancestry SectVersion="1" SectionFlags="0" SubIdent="0" Template="false">
	<MainGUID>F938E33A-329D-4A36-BE3E-85E126820996</MainGUID>
	<MainGUID>103E8D2C-8230-42E1-9597-46F84CCE28C0</MainGUID>
	<MainGUID>56A4A77E-2509-450D-94D0-A816189B7DF4</MainGUID>
	<MainGUID>06BA412F-7262-4221-A9B3-1A3E410E9170</MainGUID>
	<MainGUID>9C72BC5B-9742-4B29-8863-75AAF5F23226</MainGUID>
</Ancestry>

<!-- GDL SCRIPT ===== GDL SCRIPT ===== GDL SCRIPT ===== GDL SCRIPT ===== GDL SCRIPT -->

<Script_3D SectVersion="20" SectionFlags="0" SubIdent="0">
<![CDATA[
!! Semisphere

if gs_detlevel_3D_m = DLEV3D_OFF then End
If gs_detlevel_3D_m = DLEV3D_SIMPLE then gs_resol = 18

if gs_shadow then
	shadow on
else
	shadow off
endif

if GLOB_CONTEXT<20 or GLOB_CONTEXT>40 then
	resol gs_resol
else
	resol 12
endif

pen gs_cont_pen

unID=1
hotspot 0,0,0,unID : unID=unID+1

material gs_prim_mat

hotspot 0,0,0,unID,angle,6 : unID=unID+1
hotspot 1,0,0,unID,angle,4+128 : unID=unID+1
hotspot 0,-1,0,unID,angle,7 : unID=unID+1
hotspot 3/4*sphere_rad*cos(angle),0,3/4*sphere_rad*sin(angle),unID,angle,5 : unID=unID+1

roty -angle

hotspot 0,0,0,unID,sphere_rad,1+128 : unID=unID+1
hotspot -1,0,0,unID,sphere_rad,3 : unID=unID+1
hotspot sphere_rad,0,0,unID,sphere_rad,2 : unID=unID+1

hotspot 0,0,0,unID,sphere_rad,1+128 : unID=unID+1
hotspot 1,0,0,unID,sphere_rad,3 : unID=unID+1
hotspot -sphere_rad,0,0,unID,sphere_rad,2 : unID=unID+1

hotspot 0,0,0,unID,sphere_rad,1+128 : unID=unID+1
hotspot 0,-1,0,unID,sphere_rad,3 : unID=unID+1
hotspot 0,sphere_rad,0,unID,sphere_rad,2 : unID=unID+1

hotspot 0,0,0,unID,sphere_rad,1+128 : unID=unID+1
hotspot 0,1,0,unID,sphere_rad,3 : unID=unID+1
hotspot 0,-sphere_rad,0,unID,sphere_rad,2 : unID=unID+1

hotspot 0,0,0,unID,sphere_rad,1+128 : unID=unID+1
hotspot 0,0,-1,unID,sphere_rad,3 : unID=unID+1
hotspot 0,0,sphere_rad,unID,sphere_rad,2 : unID=unID+1

RESOL gs_resol
ellips sphere_rad,sphere_rad
]]>
</Script_3D>

<!-- GDL SCRIPT ===== GDL SCRIPT ===== GDL SCRIPT ===== GDL SCRIPT ===== GDL SCRIPT -->

<Script_2D SectVersion="20" SectionFlags="0" SubIdent="0">
<![CDATA[
pen gs_cont_pen

unID	= 1
hLineID = 1000

hotspot2 0,0,unID : unID=unID+1

hotspot2 0,0,unID,sphere_rad,1+128 : unID=unID+1
hotspot2 -1,0,unID,sphere_rad,3 : unID=unID+1
hotspot2 sphere_rad*cos(angle),0,unID,sphere_rad,2 : unID=unID+1

hotspot2 0,0,unID,sphere_rad,1+128 : unID=unID+1
hotspot2 1,0,unID,sphere_rad,3 : unID=unID+1
hotspot2 -sphere_rad*cos(angle),0,unID,sphere_rad,2 : unID=unID+1

hotspot2 0,0,unID,sphere_rad,1+128 : unID=unID+1
hotspot2 0,-1,unID,sphere_rad,3 : unID=unID+1
hotspot2 0,sphere_rad,unID,sphere_rad,2 : unID=unID+1

hotspot2 0,0,unID,sphere_rad,1+128 : unID=unID+1
hotspot2 0,1,unID,sphere_rad,3 : unID=unID+1
hotspot2 0,-sphere_rad,unID,sphere_rad,2 : unID=unID+1

fill gs_fill_type
if abs(angle) < eps  then
	poly2_b	2, 1+2+64, gs_fill_pen, gs_back_pen,
			0, 0, 901,
			sphere_rad, 360, 4001

	hotarc2 0,0,sphere_rad,0,180, hLineID : hLineID = hLineID + 1
	hotarc2 0,0,sphere_rad,180,360, hLineID : hLineID = hLineID + 1
else
	project2{2} 3, 270, 32+3, gs_back_pen, 0, 0, 90
endif

]]>
</Script_2D>

<!-- GDL SCRIPT ===== GDL SCRIPT ===== GDL SCRIPT ===== GDL SCRIPT ===== GDL SCRIPT -->

<Script_1D SectVersion="20" SectionFlags="0" SubIdent="0">
<![CDATA[
! const values for parameter: gs_detlevel_3D_m
DLEV3D_OFF      = 0
DLEV3D_SIMPLE   = 1
DLEV3D_DETAILED = 2

eps=0.00001
]]>
</Script_1D>

<!-- GDL SCRIPT ===== GDL SCRIPT ===== GDL SCRIPT ===== GDL SCRIPT ===== GDL SCRIPT -->

<Script_PR SectVersion="20" SectionFlags="0" SubIdent="0">
<![CDATA[]]>
</Script_PR>

<!-- GDL SCRIPT ===== GDL SCRIPT ===== GDL SCRIPT ===== GDL SCRIPT ===== GDL SCRIPT -->

<Script_UI SectVersion="20" SectionFlags="0" SubIdent="0">
<![CDATA[]]>
</Script_UI>

<!-- GDL SCRIPT ===== GDL SCRIPT ===== GDL SCRIPT ===== GDL SCRIPT ===== GDL SCRIPT -->

<Script_VL SectVersion="20" SectionFlags="0" SubIdent="0">
<![CDATA[
call "FM_types" parameters all

values{2} "gs_detlevel_3D_m" 	DLEV3D_DETAILED, `Детальный`,
								DLEV3D_SIMPLE, `Простой`,
								DLEV3D_OFF, `Откл.`
parameters a=sphere_rad*2,b=sphere_rad*2,zzyzx=sphere_rad*2
lock "a","b","zzyzx"

if gs_cont_pen=0 then parameters gs_cont_pen=2
if gs_fill_pen=0 then parameters gs_fill_pen=91

If gs_resol<3 then parameters gs_resol=3
if gs_detlevel_3D_m = DLEV3D_SIMPLE then lock "gs_resol"


VALUES "ANGLE" range [0,360]
if abs(angle)>=eps AND abs(angle-180)>=eps then lock "gs_fill_pen"


]]>
</Script_VL>

<!-- GDL SCRIPT ===== GDL SCRIPT ===== GDL SCRIPT ===== GDL SCRIPT ===== GDL SCRIPT -->

<Comment SectVersion="20" SectionFlags="0" SubIdent="0">
<![CDATA[Вращаемая полусфера.]]>
</Comment>

<Keywords SectVersion="1" SectionFlags="0" SubIdent="0">
<![CDATA[]]>
</Keywords>

<ParamSection SectVersion="26" SectionFlags="0" SubIdent="0">
	<ParamSectHeader>
		<Version>26</Version>
		<AutoHotspots>false</AutoHotspots>
		<StatBits>
			<STBit_FixSize/>
		</StatBits>
		<WDLeftFrame>0</WDLeftFrame>
		<WDRightFrame>0</WDRightFrame>
		<WDTopFrame>0</WDTopFrame>
		<WDBotFrame>0</WDBotFrame>
		<LayFlags>65535</LayFlags>
		<WDMirrorThickness>0</WDMirrorThickness>
		<WDWallInset>0</WDWallInset>
		<SymbolColor>0</SymbolColor>
	</ParamSectHeader>
	<Parameters>
		<Length Name="A">
			<Description><![CDATA["Размер 1"]]></Description>
			<Fix/>
			<Value>1</Value>
		</Length>
		<Length Name="B">
			<Description><![CDATA["Размер 2"]]></Description>
			<Fix/>
			<Value>1</Value>
		</Length>
		<Length Name="ZZYZX">
			<Description><![CDATA["Высота"]]></Description>
			<Fix/>
			<Value>1</Value>
		</Length>
		<Integer Name="gs_detlevel_3D_m">
			<Description><![CDATA["3D"]]></Description>
			<Value>2</Value>
		</Integer>
		<Length Name="sphere_rad">
			<Description><![CDATA["Радиус Сферы"]]></Description>
			<Value>0.5</Value>
		</Length>
		<Angle Name="angle">
			<Description><![CDATA["Угол поворота"]]></Description>
			<Value>0</Value>
		</Angle>

		<!-- gs_3D_representation: PARAMETER BLOCK ===== PARAMETER BLOCK ===== PARAMETER BLOCK ===== PARAMETER BLOCK -->

		<Title Name="gs_3D_representation">
			<Description><![CDATA["3D-отображение"]]></Description>
		</Title>
		<Integer Name="gs_resol">
			<Description><![CDATA["Аппроксимация"]]></Description>
			<Flags>
				<ParFlg_Child/>
			</Flags>
			<Value>36</Value>
		</Integer>
		<Boolean Name="gs_shadow">
			<Description><![CDATA["Отбрасывание Теней"]]></Description>
			<Flags>
				<ParFlg_Child/>
			</Flags>
			<Value>1</Value>
		</Boolean>
		<Boolean Name="AC_show2DHotspotsIn3D">
			<Description><![CDATA["Показ Узловых 2D Точек в 3D"]]></Description>
			<Fix/>
			<Flags>
				<ParFlg_Hidden/>
			</Flags>
			<Value>1</Value>
		</Boolean>
		<Length Name="ac_bottomlevel">
			<Description><![CDATA["Отметка Низа"]]></Description>
			<Fix/>
			<Flags>
				<ParFlg_Hidden/>
			</Flags>
			<Value>1</Value>
		</Length>
		<Length Name="ac_toplevel">
			<Description><![CDATA["Отметка Верха"]]></Description>
			<Fix/>
			<Flags>
				<ParFlg_Hidden/>
			</Flags>
			<Value>0</Value>
		</Length>

		<!-- gs_2D_representation: PARAMETER BLOCK ===== PARAMETER BLOCK ===== PARAMETER BLOCK ===== PARAMETER BLOCK -->

		<Title Name="gs_2D_representation">
			<Description><![CDATA["2D-отображение"]]></Description>
		</Title>
		<PenColor Name="gs_cont_pen">
			<Description><![CDATA["Перо Контура"]]></Description>
			<Flags>
				<ParFlg_Child/>
			</Flags>
			<Value>4</Value>
		</PenColor>
		<FillPattern Name="gs_fill_type">
			<Description><![CDATA["Тип Штриховки"]]></Description>
			<Flags>
				<ParFlg_Child/>
			</Flags>
			<Value>65</Value>
		</FillPattern>
		<PenColor Name="gs_fill_pen">
			<Description><![CDATA["Перо Штриховки"]]></Description>
			<Flags>
				<ParFlg_Child/>
			</Flags>
			<Value>19</Value>
		</PenColor>
		<PenColor Name="gs_back_pen">
			<Description><![CDATA["Перо Фона Штриховки"]]></Description>
			<Flags>
				<ParFlg_Child/>
			</Flags>
			<Value>19</Value>
		</PenColor>

		<!-- gs_material: PARAMETER BLOCK ===== PARAMETER BLOCK ===== PARAMETER BLOCK ===== PARAMETER BLOCK -->

		<Title Name="gs_material">
			<Description><![CDATA["Покрытия"]]></Description>
		</Title>
		<Material Name="gs_prim_mat">
			<Description><![CDATA["Сфера"]]></Description>
			<Flags>
				<ParFlg_Child/>
			</Flags>
			<Value>60</Value>
		</Material>

		<!-- gs_list: PARAMETER BLOCK ===== PARAMETER BLOCK ===== PARAMETER BLOCK ===== PARAMETER BLOCK -->

		<Title Name="gs_list">
			<Description><![CDATA["Параметры Спецификаций"]]></Description>
		</Title>
		<RealNum Name="gs_list_cost">
			<Description><![CDATA["Цена"]]></Description>
			<Flags>
				<ParFlg_Child/>
			</Flags>
			<Value>0</Value>
		</RealNum>
		<String Name="gs_list_manufacturer">
			<Description><![CDATA["Производитель"]]></Description>
			<Flags>
				<ParFlg_Child/>
			</Flags>
			<Value><![CDATA[""]]></Value>
		</String>
		<String Name="gs_list_note">
			<Description><![CDATA["Примечания"]]></Description>
			<Flags>
				<ParFlg_Child/>
			</Flags>
			<Value><![CDATA[""]]></Value>
		</String>
		<String Name="gs_list_location">
			<Description><![CDATA["Расположение"]]></Description>
			<Flags>
				<ParFlg_Child/>
			</Flags>
			<Value><![CDATA[""]]></Value>
		</String>
		<String Name="gs_list_accessories">
			<Description><![CDATA["Аксессуары"]]></Description>
			<Flags>
				<ParFlg_Child/>
			</Flags>
			<Value><![CDATA[""]]></Value>
		</String>
		<String Name="FM_Type">
			<Description><![CDATA["Тип Группы"]]></Description>
			<Flags>
				<ParFlg_Child/>
			</Flags>
			<Value><![CDATA["Другой"]]></Value>
		</String>
		<Integer Name="iFMType">
			<Description><![CDATA["Тип Группы"]]></Description>
			<Flags>
				<ParFlg_Child/>
				<ParFlg_Hidden/>
			</Flags>
			<Value>25</Value>
		</Integer>
		<String Name="FM_InventoryNumber">
			<Description><![CDATA["Инвентарный Номер"]]></Description>
			<Flags>
				<ParFlg_Child/>
			</Flags>
			<Value><![CDATA[""]]></Value>
		</String>
		<String Name="FM_SerialNumber">
			<Description><![CDATA["Серийный Номер"]]></Description>
			<Flags>
				<ParFlg_Child/>
			</Flags>
			<Value><![CDATA[""]]></Value>
		</String>
		<String Name="FM_ProductionYear">
			<Description><![CDATA["Год Производства"]]></Description>
			<Flags>
				<ParFlg_Child/>
			</Flags>
			<Value><![CDATA[""]]></Value>
		</String>
		<RealNum Name="FM_ObjectWeight">
			<Description><![CDATA["Вес Изделия"]]></Description>
			<Flags>
				<ParFlg_Child/>
			</Flags>
			<Value>0</Value>
		</RealNum>
		<String Name="FM_ObjectWeightUnit">
			<Description><![CDATA["Единица Веса"]]></Description>
			<Flags>
				<ParFlg_Child/>
			</Flags>
			<Value><![CDATA["кг"]]></Value>
		</String>
		<String Name="gs_list_custom1">
			<Description><![CDATA["Пользовательское Значение 1"]]></Description>
			<Flags>
				<ParFlg_Child/>
			</Flags>
			<Value><![CDATA[""]]></Value>
		</String>
		<String Name="gs_list_custom2">
			<Description><![CDATA["Пользовательское Значение 2"]]></Description>
			<Flags>
				<ParFlg_Child/>
			</Flags>
			<Value><![CDATA[""]]></Value>
		</String>
		<String Name="gs_list_custom3">
			<Description><![CDATA["Пользовательское Значение 3"]]></Description>
			<Flags>
				<ParFlg_Child/>
			</Flags>
			<Value><![CDATA[""]]></Value>
		</String>
		<String Name="gs_list_custom4">
			<Description><![CDATA["Пользовательское Значение 4"]]></Description>
			<Flags>
				<ParFlg_Child/>
			</Flags>
			<Value><![CDATA[""]]></Value>
		</String>
		<String Name="gs_list_custom5">
			<Description><![CDATA["Пользовательское Значение 5"]]></Description>
			<Flags>
				<ParFlg_Child/>
			</Flags>
			<Value><![CDATA[""]]></Value>
		</String>
	</Parameters>
</ParamSection>

<Picture MIME="image/png" SectVersion="19" SectionFlags="0" SubIdent="0" length_in_bytes="3826" platform="Win">
	<![CDATA[
	696D6167652F706E670089504E470D0A1A0A0000000D49484452000000800000
	00800803000000F4E091F900000252504C5445FFFFFFF5F5F5F4F4F47A7A7A83
	83837E7E7E8282827B7B7B8585857575757272727474747979796F6F6F737373
	A8A8A89B9B9B6C6C6C8D8D8D6D6D6D939393898989888888A0A0A09292928E8E
	8EFEFEFEF9F9F9F7F7F85D5D5DF4F4F56262626161616B6B6B6A6A6A5F5F5F64
	64645C5C5C6363636868685E5E5EEFEFF0606060DDDDDEE8E8E9666666F5F5F6
	F6F6F7F1F1F2ECECEBE2E2E3656565E7E7E8696969F2F2F3F3F3F4F1F1F0EEEE
	EFEDEDEEDCDCDD5B5B5BE3E3E2E4E4E5E6E6E7DADADBD7D7D8C9C9CAEBEBEC5A
	5A5AEBEBEAF0F0F1ECECEDE1E1E2C6C6C7F0F0EFE6E6E5E9E9EAD8D8D8E7E7E7
	E3E3E3D4D4D4DADADAD2D2D2F1F1F1CECECEEDEDEDDEDEDEEBEBEBEAEAEAD5D5
	D5E9E9E9A9A9A9EEEEEEDCDCDCB9B9B9E0E0E0F0F0F0B4B4B4D0D0D0E6E6E6E8
	E8E8DBDBDBADADADA5A5A5EFEFEFB7B7B7AAAAAADFDFDFBFBFBFE5E5E5959595
	AFAFAF8C8C8C919191B6B6B68A8A8AD7D7D79C9C9CD9D9D99A9A9AE2E2E2E4E4
	E4BBBBBBE1E1E1C5C5C5D6D6D6C8C8C8C3C3C3BEBEBEA2A2A2DDDDDDABABABCF
	CFCFB0B0B0878787C9C9C9BCBCBCECECECCCCCCCC1C1C1C6C6C69E9E9EB1B1B1
	D1D1D1FDFDFD9F9F9FA6A6A6C2C2C2BABABAF6F6F6B2B2B2808080B3B3B3D3D3
	D3A3A3A3949494BDBDBDF2F2F2969696C7C7C78B8B8B979797F3F3F36E6E6EFC
	FCFCC0C0C0717171B8B8B8999999CBCBCBA7A7A7FAFAFA7D7D7DA1A1A1F8F8F8
	777777909090A4A4A4676767C4C4C4767676868686CACACAFBFBFB9D9D9D8F8F
	8F818181B5B5B5787878CDCDCD989898848484707070AEAEAEACACAC7F7F7F7C
	7C7CF7F7F7D6DFE8C900000C5149444154785EEC93D3B25D411445EF0F6E5BC7
	B66DEBDAB663DBF9AFACD3BB52B7F27A90A71E3F3047CFB97A614230180C0683
	C1603018CCDB4D1BE96A1044AAACD06CB0E8E47EAFFCB7ECFB43552CF3C7A5F5
	F55A6FC392B06F45DB9EA6164DD4788A9BFFC36DA4413B789E6F395A2DFEF36D
	B752AA0E433D8BDF1ED5F656D3CF0316B6BF32C7F43CA328A90CE366980C01DD
	EF2EB7C0E1B854BDAC15AE3F6E459BDEC5D3F8D15E959C47FAC5992A1A0D6B2E
	4F51B9623128360C269352E865073F785301858382DFBEF4BD79574FEF27DFAF
	557CB3DE5DC85B734E15E172916498CA59C5869B2114D44265F472182A58123B
	ED1F9AF7713A92FC1A0BB867D9BD2F9C77C97D13499265B020C348015A000554
	42E860C36F6F7B346FFD5D76FF64FBD7CDEEACE239959404413711040124C0C1
	543018A24CB3A80498010C963C81B5FA6236124F3E7A156167B13D27AB82EE7B
	0049400FA642705C02CD3AF87F0D56B347F1D8EBA7DFBE88D3E66F4AB2EEB301
	1C604380C45801193829AB39031874477F4F51830EC6069DEDAB73EDC9741F4F
	D2CDEC43804320055D47433C18A0154AA8831DB803B4C2B358E7C3A7173F0793
	E7FF21D54C18A2BAAE381E66601616112720065140D4C62CA666AB4DBAEF8B54
	7C25B608750A5AA749B0A134B8D5A4A616824625C6C954EC54192D8D954054A8
	3A250E7598EF95B3DCFBCE5B66E6C1E47E81F39B73FEE77FCE7D77CABABAA21C
	5B8E2050128080AB00CDF0DFAB7F06532243A8BDFDE9FD4FAE7C766D3E1DAC6B
	3F172BB1FAD1B128444FD90E333002978108769DBC7C010C01BA912C09FCE0F6
	DAB7271F7F30144AF8A7B685779702D014EB31C3FBF008C273560254622F1982
	08918BB07AB2714D7D265BBDAA7DE36F4A505F5794C2FB6C4723180613900E8E
	9D78AD175B018B701727835904904143607A616AEBE6FBB995018CA762465207
	2FC3636360822789A01B08A808BB2F6027482F4E7CB81A8A8032082FB6BD1AEA
	58517CA30792AF82CB110233076348D00F760045D8D36749C1A3DA439882C135
	0D5884486BF36CEF4AE2C724BCED3808741106F63F7570F8A44D0568479482A1
	F9F4D2EC54A4AEE5CE9E65C74F4653123D1F8322D03278A1FF287AB2A8805B51
	52E0AFAA89D46D018295C78F9B47003401A5E0EBD809A8024E01B9D1FB3017A9
	11B40AA6172A6B22918D42E01D5FC2E745B017015A111B016578461BF2C7FF7F
	1DBD00DCE8AD86F2AC3FBC5873BD6ECB33EF79033C913454FC789E6327601D52
	23801B758221F79DA11A1CD7328491D0B86E28042AA844829639EF5EC849FC7C
	47644076C029C01AEC7F0DEDB00F6BF0112E895283CFAE8D042AAAABA6164107
	CD999C57FC684AC27B12983538304066E4EC03A8C1C32B28C34470AE12095A9B
	078B03CCD8E3E7E40881A50886016EC49DF80DAA01F4010C847FF1402037A41A
	800C67AB88A06DF3BEE2DB47D2E7082FC70D2035781A6A405EC48DF8176A44D8
	0F712F803EC01A845701C1F5C88BCDA345007C86C497C82E023740F7816FA208
	7031010010012DA83C91541FCC5531417BCDDEC203D040FD49780F02A708D009
	FA3E47159A23718245508F7D1046026885CD8D85B7CF94C4CF7B6C45781909A2
	488022E8E791C856C400EC046086D4880B73488032683E5BC00152A60072850E
	03B852802ADCA1006422E25A026E8C2A0411F86781A0B2128AF07C5B47810EF4
	882F297003E062D4DB094B81F2C24BFFFEDF796A03A54210C1021070119AFF99
	DF02750172458E27C06904D08B197A218D03506110004088D88B2FB6E41B0A71
	E880D201BA3B5C003C10551B64B2C16A4C01125CAFDB1698C9B3814B02BC089E
	05800D44207D0800680408804670DC3482D50F0920B154CD04508448EBE637DD
	16400AB4C75F3F83677DB1141806031CB0007C6002D42A00D84DD3D37E9502D4
	E196D9943301A2405B7846F002F81E0248090400C6110384D2D3414D803AFCFE
	79B7021CF1672CC70BE0AB760D48091860500066E7D80CB604E38E2D245522C0
	0F15C0B7188057128B063E7CFB21AC65388E8240202A68FEC02B01B65308C0D5
	861754175CB203D4CF072A96827E246015D4B5348C5B13A04D58E27B0260FC97
	AC00EC84A7B511B10FA8120C2100A780DD28D2B6C9FAFDE296912A2B01C06644
	B4155E9659E0068014402B6A2FF8CAA7168094362189BF6C001E46380D6527D3
	B340DA3094AE98460249C1338B86EC215C81E503B011E969C87B3103C0E58896
	4206602754004060EDC4D64DA3D645B06CD900A24106789217F363FB9FFAF62E
	5A8BF542721EC7B1B26205000422C34D9F4805C405BD24B05D005C4ECC36C04E
	4C571304B87F64F27102C8564C4B0AA80653495D0118035F56831D47DFA09BC9
	69D88AC90608003622D80700A00100B806FE052543A8C155BD89B9E7D0722B00
	3E48129026E0B55CD90003E038CEA4B39002E944EA83FB0AA02CEA2BC5860480
	25001ADC232B2174213931AC648DB0906412099502A941FBD20DB58A19C501D6
	17E801998500605E0BAEF2CD48BAF070E33AD8883440B0BA5A036CDD7A424920
	290032098BCE424980F8201B315F0B5883B891A10FC14E589E4E500D30053491
	A6F0A2C622B815138065CF6201B02DE56A258551244D8036301F48DB6AA01AF1
	364B209612003912DE2D41E901DE46D4BDC8722BD01AD45DE80008F3401AB9C1
	1A64002658E142D8833ECC4D482E0012A00A8004601F827B0936016C6481745A
	03F84D153E5FEDA36D980098C033BEDB04B40F63135205B40DC1AD0047D1E141
	D02001B0080080CC1055D8D68D00B115014802C406A902DFE17B9992C0C72881
	09B8154CB2060940CC90C741DBC661DC0562C6F2009C3753435CE828EF02E4C3
	AA09B504C0076114114042009417B69CC526E81180122E45E442FA66AC7C1827
	112F035A02E5818000481B34FF150066BA004008BCE3B309C92A0009A0410415
	4017E217346E4265430C9076B7C1AB1771168F19294B0AE29EF15D77A2017832
	E04F64DFFD89AD02CA0586E6CB1540D60650C3D320EE0D201F06DC05E075943F
	D45A26A1AEC061A840BD0058FA1001360E314092018460051F67940B2A1B4617
	3A8E2E64AB40A81C0840036E806B1A4008DC087147FC97AD5F49F9C182122026
	808348D9202EA423190F80A81320BE5D00F27F9F7B4E2B509B102480B6419903
	AA0770107800EC250021902C6CCFFF8DF4258B02B905B8077119A37514E6C0EB
	175505A009438501EA19406A200472F8422E0D6053209A202680C700BAA04850
	F5C04861806D83782FEE8911403102C7877AFD56C109804580E6205C4A711FB7
	4B107B209329D4059BE83341B2279A2C4E50E6F8FD9604B0022F5FD009D02EA8
	25883DE002D03E70279CE485443D4F797DA4D7F1BFA6E33F0D1EC4EF55ECC238
	884901900091A006702F04340A50055003C713D1B312DD159F0AA05FEC701343
	05E2182217A604900B5205AE3530800C2301683967BE90AA14147FA7E1F849FD
	60F703B40065C2F46E4B096005E83944123401B23680A9F6C3338F0901033082
	E753D54E7E2CA3298805D00A84EB0078002B404B30E40008AA69B878672DC7E7
	D39414820DF9C2FBDC0F96F44ED3A91E6D2901EC01DA84240119AD41B91EB62E
	5E72BC93FB98C09905EB6B25EB8FE3B300E0BD923D1014881EC409D877085A40
	F72025C0095059F7A0D3FD569C2221BA8F84E7FEEBF91137C08FDF780504C01D
	405388A680B400F6E0484803707CDA09AB22D9B337F23D97CD0042DEF0927EF9
	FDE04028007CB3660BD00A04059C5A7BEE88998010C56700C880BF6A31F1C768
	A117B3199F230996477B0CFF53F3BF13FD3BC801D0825800A04032E147FBC004
	45015201B201FFAAF0BAB346B147BB7B653E41B044377F7ED75ED0DF0BD480E8
	002800EC001A02E841D882A609CE5B01B2D373E1F2B5BB6F783E5CE628304797
	EACB1F37E86F1396FFCF8CA200700DC04D50B72024C00690585A984DACBEDBE3
	159DD330DE14C7B0CEDFBF13CB8FFDF733337E9F12005B006E82A8406C01AA00
	F740003ED52FBD553BDABDA207FC5BB9320A2EF155FDD9805E39B80B1F4A5100
	6441C75181D882174901935758829972F83C58B1E6D49BC3F152FE44722F1E67
	F1C5E46F2B3FE77F0FC108E00E1C250B22059C27139E80394CB78191C0F452BA
	E1C8A3BBBDA9C74A3FE3E34DB9386400A363FE5100C7F6D31F67F8CF743C8470
	0D502DA03E0EAF7B70E5D4DF3F3A18F3D2DCF244F1C4BDA6269F61C4C6D080F5
	7F9768049000203CFF7CC8FF44EDBE3FFCED1F372F9FE86EF20A5052516E35E5
	A2D1AE03FD03C7DEEB1CC62A800F00C6CDD39F9FB9797278D740C7982FF745BB
	70400200080401EC735CEA0B6150C51082B0B17923CDD96BCDBF00006003476B
	961151D288B50000000049454E44AE426082
	]]>
</Picture>

<CalledMacros SectVersion="2" SectionFlags="0" SubIdent="0">
	<Macro>
		<MName><![CDATA["FM_types"]]></MName>
		<MainGUID>2759D2DF-AA8E-44D1-AD1D-261581266B34</MainGUID>
	</Macro>
</CalledMacros>

<Copyright SectVersion="1" SectionFlags="0" SubIdent="0">
	<Author>GRAPHISOFT</Author>
	<License>
		<Type>CC BY-ND</Type>
		<Version>3.0</Version>
	</License>
</Copyright>

<MigrationTable SectVersion="1" SectionFlags="0" SubIdent="0">
	<MigrationTableElement>
		<MainGUID>B2F5D7F5-5DC2-4C39-8209-FB09DC55C2BD</MainGUID>
		<Version>18</Version>
		<Name><![CDATA[""]]></Name>
		<AutoMigration>true</AutoMigration>
	</MigrationTableElement>
</MigrationTable>

</Symbol>
